{
  "student_id": "S0403",
  "career_path": "Data",
  "career_source": "Prediction",
  "generated_at": "2025-11-29",
  "certification_path": [
    "Google Data Analytics",
    "Azure Data Scientist Associate",
    "IBM Data Science"
  ],
  "stages": [
    {
      "stage": "Beginner",
      "duration": "4-6 weeks",
      "focus": "Fundamentals & Top Gaps",
      "skills": [
        "flask, computer vision, routing, sql, aws",
        "microservices, aws, c, ansible, routing, ci/cd",
        "microservices, aws, c, ansible, routing, ci/cd, sql, docker",
        "rest apis, git, tcp/ip, terraform, python, aws, docker, sql",
        "rest apis, git, tcp/ip, terraform, python, node.js"
      ],
      "courses": [
        {
          "course_name": "AWS Data Analytics - Cohort 9 (Part 1)",
          "provider": "AWS",
          "level": "Advanced",
          "score": 0.5232542753219604,
          "similarity": 0.7054237723350525,
          "coverage": 0.0,
          "covers_skills": []
        },
        {
          "course_name": "AWS Data Analytics - Cohort 12 (Part 2)",
          "provider": "AWS",
          "level": "Advanced",
          "score": 0.5201889872550964,
          "similarity": 0.7003149390220642,
          "coverage": 0.0,
          "covers_skills": []
        },
        {
          "course_name": "AWS Data Analytics - Cohort 6 (Part 3)",
          "provider": "AWS",
          "level": "Advanced",
          "score": 0.5164478421211243,
          "similarity": 0.6940796971321106,
          "coverage": 0.0,
          "covers_skills": []
        }
      ],
      "projects": [
        {
          "title": "Exploratory Data Analysis on Titanic Dataset",
          "skills": [
            "python",
            "pandas",
            "matplotlib"
          ],
          "type": "Analysis",
          "difficulty": "Beginner"
        },
        {
          "title": "Flask, Computer Vision, Routing, Sql, Aws & Microservices, Aws, C, Ansible, Routing, Ci/Cd & Microservices, Aws, C, Ansible, Routing, Ci/Cd, Sql, Docker Integration Lab",
          "description": "Set up a practical lab environment to experiment with Flask, Computer Vision, Routing, Sql, Aws & Microservices, Aws, C, Ansible, Routing, Ci/Cd & Microservices, Aws, C, Ansible, Routing, Ci/Cd, Sql, Docker configurations and troubleshooting.",
          "difficulty": "Beginner",
          "skills_covered": [
            "flask, computer vision, routing, sql, aws",
            "microservices, aws, c, ansible, routing, ci/cd",
            "microservices, aws, c, ansible, routing, ci/cd, sql, docker"
          ]
        }
      ]
    },
    {
      "stage": "Intermediate",
      "duration": "6-8 weeks",
      "focus": "Application & Certification",
      "skills": [],
      "courses": [
        {
          "course_name": "AWS Data Analytics - Cohort 3 (Part 3)",
          "provider": "AWS",
          "level": "Advanced",
          "score": 0.5138651132583618,
          "similarity": 0.6897751688957214,
          "coverage": 0.0,
          "covers_skills": []
        },
        {
          "course_name": "AWS Data Analytics - Cohort 6 (Part 1)",
          "provider": "AWS",
          "level": "Advanced",
          "score": 0.5120342969894409,
          "similarity": 0.6867238283157349,
          "coverage": 0.0,
          "covers_skills": []
        },
        {
          "course_name": "Huawei Data Warehouse and BI - Cohort 12 (Part 3)",
          "provider": "Huawei",
          "level": "Advanced",
          "score": 0.5311786532402039,
          "similarity": 0.7186310291290283,
          "coverage": 0.0,
          "covers_skills": []
        }
      ],
      "projects": [
        {
          "title": "E-commerce Sales Dashboard",
          "skills": [
            "sql",
            "tableau",
            "data cleaning"
          ],
          "type": "Visualization",
          "difficulty": "Intermediate"
        },
        {
          "title": "Build a Mid-Level Data Analyst Pipeline using Flask, Computer Vision, Routing, Sql, Aws & Microservices, Aws, C, Ansible, Routing, Ci/Cd & Microservices, Aws, C, Ansible, Routing, Ci/Cd, Sql, Docker",
          "description": "Create a comprehensive project that demonstrates your mastery of Flask, Computer Vision, Routing, Sql, Aws & Microservices, Aws, C, Ansible, Routing, Ci/Cd & Microservices, Aws, C, Ansible, Routing, Ci/Cd, Sql, Docker. Focus on real-world application.",
          "difficulty": "Intermediate",
          "skills_covered": [
            "flask, computer vision, routing, sql, aws",
            "microservices, aws, c, ansible, routing, ci/cd",
            "microservices, aws, c, ansible, routing, ci/cd, sql, docker"
          ]
        }
      ]
    },
    {
      "stage": "Advanced",
      "duration": "8-10 weeks",
      "focus": "Mastery & Job Readiness",
      "skills": [],
      "courses": [
        {
          "course_name": "Huawei Data Warehouse and BI - Cohort 6 (Part 1)",
          "provider": "Huawei",
          "level": "Advanced",
          "score": 0.5284805297851562,
          "similarity": 0.7141342163085938,
          "coverage": 0.0,
          "covers_skills": []
        },
        {
          "course_name": "Huawei Data Warehouse and BI - Cohort 6 (Part 3)",
          "provider": "Huawei",
          "level": "Advanced",
          "score": 0.527428925037384,
          "similarity": 0.7123815417289734,
          "coverage": 0.0,
          "covers_skills": []
        },
        {
          "course_name": "Big Data Developer - Cohort 3 (Part 2)",
          "provider": "Huawei",
          "level": "Advanced",
          "score": 0.5138511657714844,
          "similarity": 0.689751923084259,
          "coverage": 0.0,
          "covers_skills": []
        }
      ],
      "projects": [
        {
          "title": "Predictive Customer Churn Model",
          "skills": [
            "scikit-learn",
            "feature engineering",
            "modeling"
          ],
          "type": "ML",
          "difficulty": "Advanced"
        },
        {
          "title": "Develop a Cloud-Native Application with Flask, Computer Vision, Routing, Sql, Aws & Microservices, Aws, C, Ansible, Routing, Ci/Cd & Microservices, Aws, C, Ansible, Routing, Ci/Cd, Sql, Docker",
          "description": "Deploy a scalable application integrating Flask, Computer Vision, Routing, Sql, Aws & Microservices, Aws, C, Ansible, Routing, Ci/Cd & Microservices, Aws, C, Ansible, Routing, Ci/Cd, Sql, Docker to solve a specific business problem.",
          "difficulty": "Advanced",
          "skills_covered": [
            "flask, computer vision, routing, sql, aws",
            "microservices, aws, c, ansible, routing, ci/cd",
            "microservices, aws, c, ansible, routing, ci/cd, sql, docker"
          ]
        }
      ],
      "internships": [
        {
          "company": "Pyramid Solutions Ltd",
          "role": "Junior Data Analyst",
          "match": 0.5352369546890259,
          "location": "Suez",
          "missing_skills": []
        },
        {
          "company": "Smartdata Labs Solutions",
          "role": "Junior Machine Learning Engineer",
          "match": 0.525799572467804,
          "location": "Suez",
          "missing_skills": []
        },
        {
          "company": "Pyramid Solutions Egypt",
          "role": "Junior Backend Developer",
          "match": 0.5237677693367004,
          "location": "Alexandria",
          "missing_skills": []
        }
      ]
    }
  ]
}