{
  "student_id": "S0840",
  "career_path": "Cloud",
  "career_source": "Prediction",
  "generated_at": "2025-11-29",
  "certification_path": [
    "AWS Cloud Practitioner",
    "AWS Solutions Architect Associate",
    "Huawei HCIA Cloud"
  ],
  "stages": [
    {
      "stage": "Beginner",
      "duration": "4-6 weeks",
      "focus": "Fundamentals & Top Gaps",
      "skills": [
        "aws, numpy, hipaa, computer vision, react, kubernetes, sql",
        "firewalls, ansible, spark, flask, hipaa, pytorch, microservices",
        "microservices, aws, c, ansible, routing, ci/cd",
        "pandas, elasticsearch, react, node.js, numpy, microservices, aws",
        "rest apis, react, javascript, pytorch, terraform, routing, aws, docker"
      ],
      "courses": [
        {
          "course_name": "AWS Academy Cloud Foundations - Cohort 9 (Part 2)",
          "provider": "AWS",
          "level": "Advanced",
          "score": 0.5435912013053894,
          "similarity": 0.7393186688423157,
          "coverage": 0.0,
          "covers_skills": []
        },
        {
          "course_name": "AWS Academy Cloud Foundations - Cohort 15 (Part 1)",
          "provider": "AWS",
          "level": "Advanced",
          "score": 0.5375798344612122,
          "similarity": 0.7292996644973755,
          "coverage": 0.0,
          "covers_skills": []
        },
        {
          "course_name": "AWS Academy Cloud Foundations - Cohort 9 (Part 1)",
          "provider": "AWS",
          "level": "Advanced",
          "score": 0.5360182523727417,
          "similarity": 0.7266970872879028,
          "coverage": 0.0,
          "covers_skills": []
        }
      ],
      "projects": [
        {
          "title": "Static Website Hosting on AWS S3",
          "skills": [
            "aws",
            "s3",
            "dns"
          ],
          "type": "Infrastructure",
          "difficulty": "Beginner"
        },
        {
          "title": "Aws, Numpy, Hipaa, Computer Vision, React, Kubernetes, Sql & Firewalls, Ansible, Spark, Flask, Hipaa, Pytorch, Microservices & Microservices, Aws, C, Ansible, Routing, Ci/Cd Integration Lab",
          "description": "Set up a practical lab environment to experiment with Aws, Numpy, Hipaa, Computer Vision, React, Kubernetes, Sql & Firewalls, Ansible, Spark, Flask, Hipaa, Pytorch, Microservices & Microservices, Aws, C, Ansible, Routing, Ci/Cd configurations and troubleshooting.",
          "difficulty": "Beginner",
          "skills_covered": [
            "aws, numpy, hipaa, computer vision, react, kubernetes, sql",
            "firewalls, ansible, spark, flask, hipaa, pytorch, microservices",
            "microservices, aws, c, ansible, routing, ci/cd"
          ]
        }
      ]
    },
    {
      "stage": "Intermediate",
      "duration": "6-8 weeks",
      "focus": "Application & Certification",
      "skills": [],
      "courses": [
        {
          "course_name": "AWS Academy Cloud Foundations - Cohort 9 (Part 1)",
          "provider": "AWS",
          "level": "Advanced",
          "score": 0.5359494686126709,
          "similarity": 0.726582407951355,
          "coverage": 0.0,
          "covers_skills": []
        },
        {
          "course_name": "AWS Academy Cloud Foundations - Cohort 15 (Part 3)",
          "provider": "AWS",
          "level": "Advanced",
          "score": 0.5338400602340698,
          "similarity": 0.7230666875839233,
          "coverage": 0.0,
          "covers_skills": []
        },
        {
          "course_name": "HCIP-Datacom - Cohort 3 (Part 1)",
          "provider": "Huawei",
          "level": "Advanced",
          "score": 0.44236353039741516,
          "similarity": 0.5706058740615845,
          "coverage": 0.0,
          "covers_skills": []
        }
      ],
      "projects": [
        {
          "title": "Serverless API with Lambda & DynamoDB",
          "skills": [
            "aws lambda",
            "api gateway",
            "nosql"
          ],
          "type": "Backend",
          "difficulty": "Intermediate"
        },
        {
          "title": "Build a Lead Cloud Engineer Pipeline using Aws, Numpy, Hipaa, Computer Vision, React, Kubernetes, Sql & Firewalls, Ansible, Spark, Flask, Hipaa, Pytorch, Microservices & Microservices, Aws, C, Ansible, Routing, Ci/Cd",
          "description": "Create a comprehensive project that demonstrates your mastery of Aws, Numpy, Hipaa, Computer Vision, React, Kubernetes, Sql & Firewalls, Ansible, Spark, Flask, Hipaa, Pytorch, Microservices & Microservices, Aws, C, Ansible, Routing, Ci/Cd. Focus on real-world application.",
          "difficulty": "Intermediate",
          "skills_covered": [
            "aws, numpy, hipaa, computer vision, react, kubernetes, sql",
            "firewalls, ansible, spark, flask, hipaa, pytorch, microservices",
            "microservices, aws, c, ansible, routing, ci/cd"
          ]
        }
      ]
    },
    {
      "stage": "Advanced",
      "duration": "8-10 weeks",
      "focus": "Mastery & Job Readiness",
      "skills": [],
      "courses": [
        {
          "course_name": "HCIP-Datacom - Cohort 12 (Part 3)",
          "provider": "Huawei",
          "level": "Advanced",
          "score": 0.4408411681652069,
          "similarity": 0.5680686235427856,
          "coverage": 0.0,
          "covers_skills": []
        },
        {
          "course_name": "HCIP-Datacom - Cohort 12 (Part 1)",
          "provider": "Huawei",
          "level": "Advanced",
          "score": 0.4400334060192108,
          "similarity": 0.5667223334312439,
          "coverage": 0.0,
          "covers_skills": []
        },
        {
          "course_name": "HCIP-Datacom - Cohort 15 (Part 1)",
          "provider": "Huawei",
          "level": "Advanced",
          "score": 0.4370172321796417,
          "similarity": 0.561695396900177,
          "coverage": 0.0,
          "covers_skills": []
        }
      ],
      "projects": [
        {
          "title": "Multi-Tier Microservices Architecture",
          "skills": [
            "kubernetes",
            "docker",
            "terraform"
          ],
          "type": "DevOps",
          "difficulty": "Advanced"
        },
        {
          "title": "Develop a Cloud-Native Application with Aws, Numpy, Hipaa, Computer Vision, React, Kubernetes, Sql & Firewalls, Ansible, Spark, Flask, Hipaa, Pytorch, Microservices & Microservices, Aws, C, Ansible, Routing, Ci/Cd",
          "description": "Deploy a scalable application integrating Aws, Numpy, Hipaa, Computer Vision, React, Kubernetes, Sql & Firewalls, Ansible, Spark, Flask, Hipaa, Pytorch, Microservices & Microservices, Aws, C, Ansible, Routing, Ci/Cd to solve a specific business problem.",
          "difficulty": "Advanced",
          "skills_covered": [
            "aws, numpy, hipaa, computer vision, react, kubernetes, sql",
            "firewalls, ansible, spark, flask, hipaa, pytorch, microservices",
            "microservices, aws, c, ansible, routing, ci/cd"
          ]
        }
      ],
      "internships": [
        {
          "company": "Pyramid Solutions Group",
          "role": "Junior Quality Assurance Engineer",
          "match": 0.5853292942047119,
          "location": "Hurghada",
          "missing_skills": []
        },
        {
          "company": "Cloudworks Egypt Ltd",
          "role": "Junior Frontend Developer",
          "match": 0.5831875801086426,
          "location": "Mansoura",
          "missing_skills": []
        },
        {
          "company": "Cloudworks Egypt Ltd",
          "role": "Junior Embedded Systems Engineer",
          "match": 0.5801363587379456,
          "location": "Hurghada",
          "missing_skills": []
        }
      ]
    }
  ]
}