{
  "student_id": "S1462",
  "career_path": "Machine Learning",
  "career_source": "Prediction",
  "generated_at": "2025-11-29",
  "certification_path": [
    "TensorFlow Developer Certificate",
    "AWS Machine Learning Specialty",
    "DeepLearning.AI"
  ],
  "stages": [
    {
      "stage": "Beginner",
      "duration": "4-6 weeks",
      "focus": "Fundamentals & Top Gaps",
      "skills": [
        "git, firewalls, azure, ci/cd, pytorch, pandas, aws, react, node.js",
        "git, rest apis, java, node.js, sql, python",
        "git, rest apis, java, sql, aws, node.js",
        "pandas, hadoop, nosql, rest apis, hipaa, sql, terraform, node.js, kubernetes, docker",
        "switching, docker, azure, pandas, aws, spark, python, tensorflow"
      ],
      "courses": [
        {
          "course_name": "AWS Academy Machine Learning for Developers - Cohort 3 (Part 3)",
          "provider": "AWS",
          "level": "Advanced",
          "score": 0.5566591024398804,
          "similarity": 0.7610984444618225,
          "coverage": 0.0,
          "covers_skills": []
        },
        {
          "course_name": "AWS Academy Machine Learning for Developers - Cohort 3 (Part 3)",
          "provider": "AWS",
          "level": "Advanced",
          "score": 0.55485600233078,
          "similarity": 0.7580932974815369,
          "coverage": 0.0,
          "covers_skills": []
        },
        {
          "course_name": "AWS Academy Machine Learning for Developers - Cohort 15 (Part 2)",
          "provider": "AWS",
          "level": "Advanced",
          "score": 0.5542861819267273,
          "similarity": 0.7571435570716858,
          "coverage": 0.0,
          "covers_skills": []
        }
      ],
      "projects": [
        {
          "title": "House Price Prediction",
          "skills": [
            "python",
            "regression",
            "scikit-learn"
          ],
          "type": "Regression",
          "difficulty": "Beginner"
        },
        {
          "title": "Git, Firewalls, Azure, Ci/Cd, Pytorch, Pandas, Aws, React, Node.Js & Git, Rest Apis, Java, Node.Js, Sql, Python & Git, Rest Apis, Java, Sql, Aws, Node.Js Integration Lab",
          "description": "Set up a practical lab environment to experiment with Git, Firewalls, Azure, Ci/Cd, Pytorch, Pandas, Aws, React, Node.Js & Git, Rest Apis, Java, Node.Js, Sql, Python & Git, Rest Apis, Java, Sql, Aws, Node.Js configurations and troubleshooting.",
          "difficulty": "Beginner",
          "skills_covered": [
            "git, firewalls, azure, ci/cd, pytorch, pandas, aws, react, node.js",
            "git, rest apis, java, node.js, sql, python",
            "git, rest apis, java, sql, aws, node.js"
          ]
        }
      ]
    },
    {
      "stage": "Intermediate",
      "duration": "6-8 weeks",
      "focus": "Application & Certification",
      "skills": [],
      "courses": [
        {
          "course_name": "AWS Academy Machine Learning for Developers - Cohort 6 (Part 1)",
          "provider": "AWS",
          "level": "Advanced",
          "score": 0.5525031089782715,
          "similarity": 0.7541718482971191,
          "coverage": 0.0,
          "covers_skills": []
        },
        {
          "course_name": "AWS Academy Machine Learning for Developers - Cohort 15 (Part 1)",
          "provider": "AWS",
          "level": "Advanced",
          "score": 0.5519689321517944,
          "similarity": 0.7532815337181091,
          "coverage": 0.0,
          "covers_skills": []
        },
        {
          "course_name": "AI Talent Program - Cohort 3 (Part 2)",
          "provider": "Huawei",
          "level": "Advanced",
          "score": 0.5256713628768921,
          "similarity": 0.709452211856842,
          "coverage": 0.0,
          "covers_skills": []
        }
      ],
      "projects": [
        {
          "title": "Image Classification with CNNs",
          "skills": [
            "tensorflow",
            "deep learning",
            "cnn"
          ],
          "type": "Computer Vision",
          "difficulty": "Intermediate"
        },
        {
          "title": "Build a Lead Machine Learning Engineer Pipeline using Git, Firewalls, Azure, Ci/Cd, Pytorch, Pandas, Aws, React, Node.Js & Git, Rest Apis, Java, Node.Js, Sql, Python & Git, Rest Apis, Java, Sql, Aws, Node.Js",
          "description": "Create a comprehensive project that demonstrates your mastery of Git, Firewalls, Azure, Ci/Cd, Pytorch, Pandas, Aws, React, Node.Js & Git, Rest Apis, Java, Node.Js, Sql, Python & Git, Rest Apis, Java, Sql, Aws, Node.Js. Focus on real-world application.",
          "difficulty": "Intermediate",
          "skills_covered": [
            "git, firewalls, azure, ci/cd, pytorch, pandas, aws, react, node.js",
            "git, rest apis, java, node.js, sql, python",
            "git, rest apis, java, sql, aws, node.js"
          ]
        }
      ]
    },
    {
      "stage": "Advanced",
      "duration": "8-10 weeks",
      "focus": "Mastery & Job Readiness",
      "skills": [],
      "courses": [
        {
          "course_name": "AI Talent Program - Cohort 6 (Part 3)",
          "provider": "Huawei",
          "level": "Advanced",
          "score": 0.5173659920692444,
          "similarity": 0.695609986782074,
          "coverage": 0.0,
          "covers_skills": []
        },
        {
          "course_name": "AI Talent Program - Cohort 15 (Part 3)",
          "provider": "Huawei",
          "level": "Advanced",
          "score": 0.5153869986534119,
          "similarity": 0.6923116445541382,
          "coverage": 0.0,
          "covers_skills": []
        },
        {
          "course_name": "AI Talent Program - Cohort 2 (Part 3)",
          "provider": "Huawei",
          "level": "Intermediate",
          "score": 0.49046528339385986,
          "similarity": 0.6841087937355042,
          "coverage": 0.0,
          "covers_skills": []
        }
      ],
      "projects": [
        {
          "title": "End-to-End NLP Chatbot",
          "skills": [
            "nlp",
            "transformers",
            "deployment"
          ],
          "type": "NLP",
          "difficulty": "Advanced"
        },
        {
          "title": "Develop a Cloud-Native Application with Git, Firewalls, Azure, Ci/Cd, Pytorch, Pandas, Aws, React, Node.Js & Git, Rest Apis, Java, Node.Js, Sql, Python & Git, Rest Apis, Java, Sql, Aws, Node.Js",
          "description": "Deploy a scalable application integrating Git, Firewalls, Azure, Ci/Cd, Pytorch, Pandas, Aws, React, Node.Js & Git, Rest Apis, Java, Node.Js, Sql, Python & Git, Rest Apis, Java, Sql, Aws, Node.Js to solve a specific business problem.",
          "difficulty": "Advanced",
          "skills_covered": [
            "git, firewalls, azure, ci/cd, pytorch, pandas, aws, react, node.js",
            "git, rest apis, java, node.js, sql, python",
            "git, rest apis, java, sql, aws, node.js"
          ]
        }
      ],
      "internships": [
        {
          "company": "Pyramid Solutions Egypt",
          "role": "Junior Machine Learning Engineer",
          "match": 0.6316698789596558,
          "location": "Aswan",
          "missing_skills": []
        },
        {
          "company": "Pyramid Solutions Group",
          "role": "Junior Machine Learning Engineer",
          "match": 0.6247572898864746,
          "location": "Aswan",
          "missing_skills": []
        },
        {
          "company": "Smartdata Labs Group",
          "role": "Junior Machine Learning Engineer",
          "match": 0.6044011116027832,
          "location": "Suez",
          "missing_skills": []
        }
      ]
    }
  ]
}